Metadata-Version: 1.1
Name: django-xperms
Version: 0.4.19
Summary: Flexible Django permissions backend
Home-page: https://github.com/formulka/django-xperms
Author: Petr Olah
Author-email: djangoguru@gmail.com
License: MIT
Download-URL: https://github.com/formulka/django-xperms/archive/0.4.19.tar.gz
Keywords: django-xperms
Platform: UNKNOWN
Classifier: Development Status :: 3 - Alpha
Classifier: Framework :: Django
Classifier: Framework :: Django :: 1.11
Classifier: Framework :: Django :: 2.0
Classifier: Framework :: Django :: 4.0
Classifier: Intended Audience :: Developers
Classifier: License :: OSI Approved :: BSD License
Classifier: Natural Language :: English
Classifier: Programming Language :: Python :: 3
Classifier: Programming Language :: Python :: 3.5
Classifier: Programming Language :: Python :: 3.6
Classifier: Programming Language :: Python :: 3.7
Classifier: Programming Language :: Python :: 3.8
